aifund/__init__.py
aifund/chart.py
aifund/collect.py
aifund/util.py
aifund-0.1.2.dist-info/licenses/LICENSE
aifund-0.1.2.dist-info/METADATA
aifund-0.1.2.dist-info/WHEEL
aifund-0.1.2.dist-info/top_level.txt
aifund-0.1.2.dist-info/RECORD
