Metadata-Version: 2.4
Name: aifund
Version: 0.1.2
Summary: AIfund 是基于 Python 的基金量化工具
Author-email: yebaige <silence_hgt@163.com>
License: MIT
Project-URL: Homepage, https://github.com/silenceTiano/aifund
Project-URL: Issues, https://github.com/silenceTiano/aifund/issues
Classifier: Programming Language :: Python :: 3
Classifier: License :: OSI Approved :: MIT License
Classifier: Operating System :: OS Independent
Requires-Python: >=3.9
License-File: LICENSE
Requires-Dist: requests>=2.31.0
Dynamic: license-file
